{
  "_buildCommand2" : {
    "command" : "prepareForIndexing",
    "enableIndexBuildArena" : true,
    "targets" : null
  },
  "buildCommand" : "build",
  "configuredTargets" : [
    {
      "guid" : "f1418eba25e7c5976ed6cb1b7e4230af9238d5068eda11b971413b1e86b1e918"
    }
  ],
  "containerPath" : "/Users/neosoft/Documents/neostore/neostore.xcodeproj",
  "continueBuildingAfterErrors" : true,
  "enableIndexBuildArena" : false,
  "hideShellScriptEnvironment" : false,
  "parameters" : {
    "action" : "indexbuild",
    "activeArchitecture" : "x86_64",
    "activeRunDestination" : {
      "disableOnlyActiveArch" : false,
      "platform" : "iphonesimulator",
      "sdk" : "iphonesimulator16.2",
      "sdkVariant" : "iphonesimulator",
      "supportedArchitectures" : [
        "x86_64"
      ],
      "targetArchitecture" : "x86_64"
    },
    "arenaInfo" : {
      "buildIntermediatesPath" : "/Users/neosoft/Documents/neostore/neostore-ccptwsfgwtsbtlggrghjtbmizfav/Index.noindex/Build/Intermediates.noindex",
      "buildProductsPath" : "/Users/neosoft/Documents/neostore/neostore-ccptwsfgwtsbtlggrghjtbmizfav/Index.noindex/Build/Products",
      "derivedDataPath" : "/Users/neosoft/Documents/neostore",
      "indexDataStoreFolderPath" : "/Users/neosoft/Documents/neostore/neostore-ccptwsfgwtsbtlggrghjtbmizfav/Index.noindex/DataStore",
      "indexEnableDataStore" : true,
      "indexPCHPath" : "/Users/neosoft/Documents/neostore/neostore-ccptwsfgwtsbtlggrghjtbmizfav/Index.noindex/PrecompiledHeaders",
      "pchPath" : "/Users/neosoft/Documents/neostore/neostore-ccptwsfgwtsbtlggrghjtbmizfav/Index.noindex/Build/Intermediates.noindex/PrecompiledHeaders"
    },
    "configurationName" : "Debug",
    "overrides" : {
      "synthesized" : {
        "table" : {
          "ENABLE_PREVIEWS" : "NO",
          "INDEX_ARENA_INFO_REGULAR_BUILD_PRODUCTS_DIR" : "/Users/neosoft/Documents/neostore/neostore-ccptwsfgwtsbtlggrghjtbmizfav/Build/Products",
          "ONLY_ACTIVE_ARCH" : "YES"
        }
      }
    }
  },
  "qos" : "utility",
  "schemeCommand" : "launch",
  "schemeCommand2" : "launch",
  "showNonLoggedProgress" : true,
  "useDryRun" : false,
  "useImplicitDependencies" : true,
  "useLegacyBuildLocations" : false,
  "useParallelTargets" : true
}